{
  "__symbolic": "module",
  "version": 1,
  "metadata": {
    "DynamicComponent": {
      "__symbolic": "class",
      "decorators": [
        {
          "__symbolic": "call",
          "expression": {
            "__symbolic": "reference",
            "module": "@angular/core",
            "name": "Component"
          },
          "arguments": [
            {
              "selector": "DynamicComponent",
              "template": ""
            }
          ]
        }
      ],
      "members": {
        "componentType": [
          {
            "__symbolic": "property",
            "decorators": [
              {
                "__symbolic": "call",
                "expression": {
                  "__symbolic": "reference",
                  "module": "@angular/core",
                  "name": "Input"
                }
              }
            ]
          }
        ],
        "componentTemplate": [
          {
            "__symbolic": "property",
            "decorators": [
              {
                "__symbolic": "call",
                "expression": {
                  "__symbolic": "reference",
                  "module": "@angular/core",
                  "name": "Input"
                }
              }
            ]
          }
        ],
        "componentInputData": [
          {
            "__symbolic": "property",
            "decorators": [
              {
                "__symbolic": "call",
                "expression": {
                  "__symbolic": "reference",
                  "module": "@angular/core",
                  "name": "Input"
                }
              }
            ]
          }
        ],
        "componentTemplateUrl": [
          {
            "__symbolic": "property",
            "decorators": [
              {
                "__symbolic": "call",
                "expression": {
                  "__symbolic": "reference",
                  "module": "@angular/core",
                  "name": "Input"
                }
              }
            ]
          }
        ],
        "componentRemoteTemplateFactory": [
          {
            "__symbolic": "property",
            "decorators": [
              {
                "__symbolic": "call",
                "expression": {
                  "__symbolic": "reference",
                  "module": "@angular/core",
                  "name": "Input"
                }
              }
            ]
          }
        ],
        "componentModules": [
          {
            "__symbolic": "property",
            "decorators": [
              {
                "__symbolic": "call",
                "expression": {
                  "__symbolic": "reference",
                  "module": "@angular/core",
                  "name": "Input"
                }
              }
            ]
          }
        ],
        "__ctor__": [
          {
            "__symbolic": "constructor",
            "parameters": [
              {
                "__symbolic": "reference",
                "module": "@angular/core",
                "name": "ElementRef"
              },
              {
                "__symbolic": "reference",
                "module": "@angular/core",
                "name": "ViewContainerRef"
              },
              {
                "__symbolic": "reference",
                "module": "@angular/core",
                "name": "Compiler"
              },
              {
                "__symbolic": "reference",
                "module": "@angular/http",
                "name": "Http"
              }
            ]
          }
        ],
        "ngOnChanges": [
          {
            "__symbolic": "method"
          }
        ],
        "getComponentTypePromise": [
          {
            "__symbolic": "method"
          }
        ],
        "loadRemoteTemplate": [
          {
            "__symbolic": "method"
          }
        ],
        "makeComponentModule": [
          {
            "__symbolic": "method"
          }
        ],
        "makeComponent": [
          {
            "__symbolic": "method"
          }
        ],
        "applyPropertiesToDynamicComponent": [
          {
            "__symbolic": "method"
          }
        ]
      }
    }
  }
}